<?xml version="1.0" encoding="utf-8"?>
<opencv_storage>
<cascade type_id="opencv-cascade-classifier">
  <stageType>BOOST</stageType>
  <featureType>LBP</featureType>
  <height>24</height>
  <width>24</width>
  <stageParams>
    <boostType>GAB</boostType>
    <minHitRate>0.9950000047683716</minHitRate>
    <maxFalseAlarm>0.5000000000000000</maxFalseAlarm>
    <weightTrimRate>0.9500000000000000</weightTrimRate>
    <maxDepth>1</maxDepth>
    <maxWeakCount>100</maxWeakCount></stageParams>
  <featureParams>
    <maxCatCount>256</maxCatCount></featureParams>
  <stageNum>20</stageNum>
  <stages>
    
    <_>
      <maxWeakCount>3</maxWeakCount>
      <stageThreshold>-0.7520892024040222</stageThreshold>
      <weakClassifiers>
        
        <_>
          <internalNodes> 0 -1 46 -345360 -262160 9394334384 -384080 -4195668 -1348 -89132500 -79695325</internalNodes>
          <leafValues>
            -0.6543210148811340 0.8888888955116272</leafValues></_>
        
        <_>
          <internalNodes> 0 -1 13 -8231325664 -3097493648 -8388624 -16 -10219544 -48099608 -626688 -16384</internalNodes>
          <leafValues>
            -0.7739216089248657 0.7278633713722229</leafValues></_>
        
        <_>
          <internalNodes> 0 -1 2 17420523776 -2147483616 -11864719376 -25445392 -22746048 -55825228 -83621750 -8556743</internalNodes>
          <leafValues>
            -0.7068563103675842 0.6761534214019775</leafValues></_></weakClassifiers></_>
    
    <_>
      <maxWeakCount>4</maxWeakCount>
      <stageThreshold>-0.4872078299522400</stageThreshold>
      <weakClassifiers>
        
        <_>
          <internalNodes> 0 -1 84 11810119840 16977625072 3891273904 34359146480 134217724 121632764 -33554432 134215679</internalNodes>
          <leafValues>
            -0.8083735704421997 0.7685696482658386</leafValues></_>
        
        <_>
          <internalNodes> 0 -1 21 30064771056 -2148040720 -4294967312 12817791984 134217724 16448504 117440511 15921842</internalNodes>
          <leafValues>
            -0.7698410153388977 0.6592915654182434</leafValues></_>
        
        <_>
          <internalNodes> 0 -1 106 -3029349952 -26751270928 -9136427120 -4194320 -6131892 100683720 -17842775 -53125648</internalNodes>
          <leafValues>
            -0.7506558895111084 0.5444605946540833</leafValues></_>
        
        <_>
          <internalNodes> 0 -1 48 -1049104 -16 -3467643920 -1107296784 -49918160 -8192 68485697 -14821504</internalNodes>
          <leafValues>
            -0.7775990366935730 0.5465461611747742</leafValues></_></weakClassifiers></_>
    
    <_>
      <maxWeakCount>4</maxWeakCount>
      <stageThreshold>-1.1592328548431396</stageThreshold>
      <weakClassifiers>
        
        <_>
          <internalNodes> 0 -1 47 -328976 -589840 -2416268640 -2147816784 -1348 -1284 -6301141 -46140885</internalNodes>
          <leafValues>
            -0.5601882934570313 0.7743113040924072</leafValues></_>
        
        <_>
          <internalNodes> 0 -1 12 -6442977296 17446207456 -4588568720 -6442450960 -17875200 11464700 -16812163 -26333184</internalNodes>
          <leafValues>
            -0.6124526262283325 0.6978127956390381</leafValues></_>
        
        <_>
          <internalNodes> 0 -1 26 -2147492016 -805832208 -537919872 -2759852048 -3146688 60680180 -3153968 -78336</internalNodes>
          <leafValues>
            -0.6114496588706970 0.6537628173828125</leafValues></_>
        
        <_>
          <internalNodes> 0 -1 8 -2147487792 34350825200 -302570272 17523699952 -16 -8454144 117373608 -130515213</internalNodes>
          <leafValues>
            -0.6854077577590942 0.5403239130973816</leafValues></_></weakClassifiers></_>
    
    <_>
      <maxWeakCount>5</maxWeakCount>
      <stageThreshold>-0.7562355995178223</stageThreshold>
      <weakClassifiers>
        
        <_>
          <internalNodes> 0 -1 96 -2148011696 32078002032 -4000 -2415935504 -76 116916216 -1310725 -4227072</internalNodes>
          <leafValues>
            -0.4051094949245453 0.7584033608436585</leafValues></_>
        
        <_>
          <internalNodes> 0 -1 33 23443391824 -4303357968 -42500304 -8388624 -54260136 -4800640 -266384 -16</internalNodes>
          <leafValues>
            -0.7388162612915039 0.5340843200683594</leafValues></_>
        
        <_>
          <internalNodes> 0 -1 57 -623888 -327696 -18462016 -1159663616 -800 0 -33818961 -9559</internalNodes>
          <leafValues>
            -0.6582943797111511 0.5339496731758118</leafValues></_>
        
        <_>
          <internalNodes> 0 -1 125 -33776 -15841886256 -7823604736 -8335163856 -16842760 -28311560 -19988511 -99627008</internalNodes>
          <leafValues>
            -0.5981323719024658 0.5323504805564880</leafValues></_>
        
        <_>
          <internalNodes> 0 -1 53 31976453088 16911433712 -537135632 -16 34861712 41891572 -83887104 -67243264</internalNodes>
          <leafValues>
            -0.6498787999153137 0.4913350641727448</leafValues></_></weakClassifiers></_>
    
    <_>
      <maxWeakCount>5</maxWeakCount>
      <stageThreshold>-0.8085358142852783</stageThreshold>
      <weakClassifiers>
        
        <_>
          <internalNodes> 0 -1 60 -2826996416 -2694842544 -268436160 -536874016 -33554604 55012208 -1052674 -1310720</internalNodes>
          <leafValues>
            -0.5278195738792419 0.6946372389793396</leafValues></_>
        
        <_>
          <internalNodes> 0 -1 7 -134221232 -671132592 -633232 -8497903760 0 -3936344 -68161945 50333186</internalNodes>
          <leafValues>
            -0.5206505060195923 0.6329920291900635</leafValues></_>
        
        <_>
          <internalNodes> 0 -1 98 23838096576 -2686451856 -16 -16 -45330456 84234220 -53280 -1050624</internalNodes>
          <leafValues>
            -0.7516061067581177 0.4232024252414703</leafValues></_>
        
        <_>
          <internalNodes> 0 -1 44 -134217744 -17251172368 -16 11742180272 -2048 62911408 -4 58457010</internalNodes>
          <leafValues>
            -0.7639313936233521 0.4123568832874298</leafValues></_>
        
        <_>
          <internalNodes> 0 -1 24 17973904464 -940748944 -16215495696 -3112214544 -5342168 133676780 -64777297 51101615</internalNodes>
          <leafValues>
            -0.5123769044876099 0.5791834592819214</leafValues></_></weakClassifiers></_>
    
    <_>
      <maxWeakCount>5</maxWeakCount>
      <stageThreshold>-0.5549971461296082</stageThreshold>
      <weakClassifiers>
        
        <_>
          <internalNodes> 0 -1 42 -279568 -16 -349264 -349536 -1088 -1280 -16778612 -8389968</internalNodes>
          <leafValues>
            -0.3763174116611481 0.7298233509063721</leafValues></_>
        
        <_>
          <internalNodes> 0 -1 6 34359736304 27849195504 -17448307728 -4295558160 -50331920 -131141396 -16844045 42656418</internalNodes>
          <leafValues>
            -0.5352765917778015 0.5659480094909668</leafValues></_>
        
        <_>
          <internalNodes> 0 -1 61 -327696 -17180196880 -813699456 -269595136 -4194352 -384 0 -5492786</internalNodes>
          <leafValues>
            -0.5678374171257019 0.4961479902267456</leafValues></_>
        
        <_>
          <internalNodes> 0 -1 123 -21546974688 14561574768 -21744168320 -21541946512 -8651788 62651132 -84938015 -119291904</internalNodes>
          <leafValues>
            -0.5706262588500977 0.4572288393974304</leafValues></_>
        
        <_>
          <internalNodes> 0 -1 9 19460932176 -579050128 535971168 -2428746128 -5571156 -262272 78533229 -83166589</internalNodes>
          <leafValues>
            -0.5344601869583130 0.4672054052352905</leafValues></_></weakClassifiers></_>
    
    <_>
      <maxWeakCount>5</maxWeakCount>
      <stageThreshold>-0.8776460289955139</stageThreshold>
      <weakClassifiers>
        
        <_>
          <internalNodes> 0 -1 105 -12632224064 -1622149136 -11043602448 -4227088 67110596 12912604 -2125840 -2097152</internalNodes>
          <leafValues>
            -0.7700348496437073 0.5943940877914429</leafValues></_>
        
        <_>
          <internalNodes> 0 -1 30 -4311744560 -21484273680 -17251172368 -20447280 -89521312 -51476480 -3072 -2143232</internalNodes>
          <leafValues>
            -0.5043668746948242 0.6151274442672730</leafValues></_>
        
        <_>
          <internalNodes> 0 -1 35 -813695808 -2064 -16 -16 -66711564 -12234888 -27296776 -8388608</internalNodes>
          <leafValues>
            -0.6808040738105774 0.4667325913906097</leafValues></_>
        
        <_>
          <internalNodes> 0 -1 119 -4295493824 33680226288 -33827904 -277874960 52033392 -2131972 -1628160 -26478720</internalNodes>
          <leafValues>
            -0.4927591383457184 0.5401885509490967</leafValues></_>
        
        <_>
          <internalNodes> 0 -1 82 -18255184064 -48 -37781696 -11832256 -68089992 -67532804 133941247 -69632</internalNodes>
          <leafValues>
            -0.6445107460021973 0.4227822124958038</leafValues></_></weakClassifiers></_>
    
    <_>
      <maxWeakCount>6</maxWeakCount>
      <stageThreshold>-1.1139287948608398</stageThreshold>
      <weakClassifiers>
        
        <_>
          <internalNodes> 0 -1 52 -85197072 -16 -5368775712 9314151072 -67129472 -67125248 0 -80008464</internalNodes>
          <leafValues>
            -0.5307556986808777 0.6258179545402527</leafValues></_>
        
        <_>
          <internalNodes> 0 -1 99 -9130090544 -9405727408 -538050624 -573571088 -44183584 -44085252 -33751045 -35655939</internalNodes>
          <leafValues>
            -0.5227634310722351 0.5049746036529541</leafValues></_>
        
        <_>
          <internalNodes> 0 -1 18 4176281584 21206925040 31270305776 -12884903184 -127226880 2632444 -16781440 -104465</internalNodes>
          <leafValues>
            -0.4983572661876679 0.5106441378593445</leafValues></_>
        
        <_>
          <internalNodes> 0 -1 111 -8749319792 -81808592 -547894000 -9126846864 -17658092 -97379568 89126171 -10657903</internalNodes>
          <leafValues>
            -0.4990860521793366 0.5060507059097290</leafValues></_>
        
        <_>
          <internalNodes> 0 -1 92 -29392434304 -21785604480 34357099952 17087609808 63520780 -37893856 57193391 -67505378</internalNodes>
          <leafValues>
            -0.5695009231567383 0.4460467398166657</leafValues></_>
        
        <_>
          <internalNodes> 0 -1 51 24095207328 -12600911136 -1277175008 -21219186144 -41026260 -963312 -8849970 -37714739</internalNodes>
          <leafValues>
            -0.6590405106544495 0.3616424500942230</leafValues></_></weakClassifiers></_>
    
    <_>
      <maxWeakCount>7</maxWeakCount>
      <stageThreshold>-0.8243625760078430</stageThreshold>
      <weakClassifiers>
        
        <_>
          <internalNodes> 0 -1 28 -2292993792 -8388624 -671090848 -16 -56349484 -12619776 -16 -4210688</internalNodes>
          <leafValues>
            -0.4972776770591736 0.6027074456214905</leafValues></_>
        
        <_>
          <internalNodes> 0 -1 112 -277613744 -526416 -1141509040 -470032 -281740 -25708808 -16777344 -4218884</internalNodes>
          <leafValues>
            -0.4383158981800079 0.5966237187385559</leafValues></_>
        
        <_>
          <internalNodes> 0 -1 69 23761154016 33219731408 33969901552 12830510832 -4743424 -7336212 -14941474 -783656</internalNodes>
          <leafValues>
            -0.6386105418205261 0.3977999985218048</leafValues></_>
        
        <_>
          <internalNodes> 0 -1 19 3874643376 21054881744 -11140301328 -7281325264 -51467524 49164284 -1054753 -85266432</internalNodes>
          <leafValues>
            -0.5512794256210327 0.4282079637050629</leafValues></_>
        
        <_>
          <internalNodes> 0 -1 73 -2969800144 922714032 -2290126032 -16659775568 -32588248 421672 -87264767 -127402257</internalNodes>
          <leafValues>
            -0.6418755054473877 0.3549866080284119</leafValues></_>
        
        <_>
          <internalNodes> 0 -1 126 -8925745168 -5436343568 23081192448 -16940832976 -29884616 67251808 -102868475 85331142</internalNodes>
          <leafValues>
            -0.4841901361942291 0.4668019413948059</leafValues></_>
        
        <_>
          <internalNodes> 0 -1 45 23481677776 -44598352 23620222960 -71701584 -15396900 -103150128 -100663296 -49275043</internalNodes>
          <leafValues>
            -0.5855734348297119 0.3879135847091675</leafValues></_></weakClassifiers></_>
    
    <_>
      <maxWeakCount>7</maxWeakCount>
      <stageThreshold>-1.2237116098403931</stageThreshold>
      <weakClassifiers>
        
        <_>
          <internalNodes> 0 -1 114 34348454208 22942840656 -4297735104 -557843280 -1548 98303992 -1050624 -4194304</internalNodes>
          <leafValues>
            -0.2518476545810700 0.7088654041290283</leafValues></_>
        
        <_>
          <internalNodes> 0 -1 97 -17866800 -34960 -131696 -537653232 -115084 -8391940 -2048 -360460</internalNodes>
          <leafValues>
            -0.4303432404994965 0.5283288359642029</leafValues></_>
        
        <_>
          <internalNodes> 0 -1 25 -12952207632 27915321328 -671350928 -2156143648 -84969224 -85037068 -67111170 -16847113</internalNodes>
          <leafValues>
            -0.4259553551673889 0.5440809130668640</leafValues></_>
        
        <_>
          <internalNodes> 0 -1 34 10535302128 34359476208 -18254414864 -262160 45609584 -8391936 -71306708 -14700048</internalNodes>
          <leafValues>
            -0.5605589151382446 0.4220733344554901</leafValues></_>
        
        <_>
          <internalNodes> 0 -1 134 19285409120 -15846080576 14201669184 -6728712416 -19398784 -26292224 -12062842 -22098008</internalNodes>
          <leafValues>
            -0.5192656517028809 0.4399855434894562</leafValues></_>
        
        <_>
          <internalNodes> 0 -1 16 1836147920 -8649248816 -11320164144 -10746567248 -89194960 123682556 -17944983 -30441809</internalNodes>
          <leafValues>
            -0.5013077259063721 0.4570254683494568</leafValues></_>
        
        <_>
          <internalNodes> 0 -1 74 -18282532544 -29817224944 34342677648 -4210960 -46153984 -55621828 -20518871 -7614528</internalNodes>
          <leafValues>
            -0.4631414115428925 0.4790246188640595</leafValues></_></weakClassifiers></_>
    
    <_>
      <maxWeakCount>7</maxWeakCount>
      <stageThreshold>-0.5544230937957764</stageThreshold>
      <weakClassifiers>
        
        <_>
          <internalNodes> 0 -1 113 -2368112 -528 -3548736 -4365486784 -4764296 -4096 0 -4198400</internalNodes>
          <leafValues>
            -0.3949716091156006 0.6082032322883606</leafValues></_>
        
        <_>
          <internalNodes> 0 -1 110 12651328304 -19401810032 12799179504 -71303728 23071728 -101577004 133660627 -74368</internalNodes>
          <leafValues>
            -0.4855885505676270 0.4785369932651520</leafValues></_>
        
        <_>
          <internalNodes> 0 -1 37 -21478639856 -13421838352 -2828304 -4295298064 49013488 -18125952 33552049 -25186560</internalNodes>
          <leafValues>
            -0.4620285332202911 0.4989669024944305</leafValues></_>
        
        <_>
          <internalNodes> 0 -1 41 -8316256512 -12364018752 -1169536960 -9365161968 -30401168 -10744704 -21268431 -1371</internalNodes>
          <leafValues>
            -0.6420643329620361 0.3624351918697357</leafValues></_>
        
        <_>
          <internalNodes> 0 -1 117 -77594704 -33288094800 -3504526848 -17150645584 -2097184 -29708288 -88966489 -129826901</internalNodes>
          <leafValues>
            -0.4820112884044647 0.4632140696048737</leafValues></_>
        
        <_>
          <internalNodes> 0 -1 65 -9918620224 -23186109504 -22190245136 -31665894768 -52133152 -8388592 -84332130 -67112722</internalNodes>
          <leafValues>
            -0.4465552568435669 0.5061788558959961</leafValues></_>
        
        <_>
          <internalNodes> 0 -1 56 -18590466336 -21474836752 -4295034144 -23425259328 -17828108 119535612 -1033 -108188929</internalNodes>
          <leafValues>
            -0.5190586447715759 0.4441480338573456</leafValues></_></weakClassifiers></_>
    
    <_>
      <maxWeakCount>7</maxWeakCount>
      <stageThreshold>-0.7161560654640198</stageThreshold>
      <weakClassifiers>
        
        <_>
          <internalNodes> 0 -1 20 -4437573648 -698351792 -19369298448 19132313840 77889532 67375072 -626691 3756</internalNodes>
          <leafValues>
            -0.4323809444904327 0.5663768053054810</leafValues></_>
        
        <_>
          <internalNodes> 0 -1 15 -31145287952 -18636265120 -31786992144 -193657584 -48661472 -38307568 -36173493 -252279</internalNodes>
          <leafValues>
            -0.4588732719421387 0.4547033011913300</leafValues></_>
        
        <_>
          <internalNodes> 0 -1 129 -22628584784 13890975728 -21698137424 -17246980112 -67109964 125826980 -85198097 -67653700</internalNodes>
          <leafValues>
            -0.5218553543090820 0.4111092388629913</leafValues></_>
        
        <_>
          <internalNodes> 0 -1 102 -1073939536 -21474837600 -20947134432 -12427756752 -5259272 -130838604 -75303142 35268143</internalNodes>
          <leafValues>
            -0.4920000731945038 0.4326725304126740</leafValues></_>
        
        <_>
          <internalNodes> 0 -1 88 33342039072 27244614128 -2307071424 -3758114592 -1605900 4194028 -18138517 -10535189</internalNodes>
          <leafValues>
            -0.4494568109512329 0.4448510706424713</leafValues></_>
        
        <_>
          <internalNodes> 0 -1 59 24813796032 -9197203536 -5718094208 -73270544 -53623800 56542668 -100766720 14517463</internalNodes>
          <leafValues>
            -0.5180826783180237 0.3888972699642181</leafValues></_>
        
        <_>
          <internalNodes> 0 -1 27 15032661616 -19137157600 -9929656784 34195460368 -6159340 -8614900 30933024 -15375851</internalNodes>
          <leafValues>
            -0.6081240773200989 0.3333222270011902</leafValues></_></weakClassifiers></_>
    
    <_>
      <maxWeakCount>8</maxWeakCount>
      <stageThreshold>-0.6743940711021423</stageThreshold>
      <weakClassifiers>
        
        <_>
          <internalNodes> 0 -1 29 -16944142992 14626059344 18357249760 -4293918800 -9437200 129449496 -81384476 33558395</internalNodes>
          <leafValues>
            -0.1790193915367127 0.6605972051620483</leafValues></_>
        
        <_>
          <internalNodes> 0 -1 128 -17725340608 25232930768 -5336937088 -2181104656 -8406840 100660980 -83886080 116342783</internalNodes>
          <leafValues>
            -0.3681024610996246 0.5139749646186829</leafValues></_>
        
        <_>
          <internalNodes> 0 -1 70 -8631886000 12473860080 -13433094784 -5136 0 66259652 -68186532 -39432407</internalNodes>
          <leafValues>
            -0.3217232525348663 0.6171553134918213</leafValues></_>
        
        <_>
          <internalNodes> 0 -1 4 3764586736 20408079088 21510246384 -15460430224 -16847648 -17814368 -49442771 -1120236</internalNodes>
          <leafValues>
            -0.4373284578323364 0.4358185231685638</leafValues></_>
        
        <_>
          <internalNodes> 0 -1 76 9210755328 -26944088608 13955473376 -18493732432 1114124 -46726776 37214201 92172479</internalNodes>
          <leafValues>
            -0.4404836893081665 0.4601220190525055</leafValues></_>
        
        <_>
          <internalNodes> 0 -1 124 -7533133904 -31960598544 -16914118144 -16244560080 -21037064 117108472 -51389476 -22237202</internalNodes>
          <leafValues>
            -0.4294152259826660 0.4452161788940430</leafValues></_>
        
        <_>
          <internalNodes> 0 -1 54 -15216472624 -4834001936 -25841696848 -1267996240 -52138256 -37105920 -20133891 -22805781</internalNodes>
          <leafValues>
            -0.3973052501678467 0.4854526817798615</leafValues></_>
        
        <_>
          <internalNodes> 0 -1 95 -13690974592 -16 31808839152 8589238128 83884028 134214492 -2097160 -2992</internalNodes>
          <leafValues>
            -0.7054683566093445 0.2697997391223908</leafValues></_></weakClassifiers></_>
    
    <_>
      <maxWeakCount>9</maxWeakCount>
      <stageThreshold>-1.2042298316955566</stageThreshold>
      <weakClassifiers>
        
        <_>
          <internalNodes> 0 -1 39 24969445136 -1353777296 -33555088 -8208 89460560 -11464868 -33562656 -8593568</internalNodes>
          <leafValues>
            -0.5905947685241699 0.5101932883262634</leafValues></_>
        
        <_>
          <internalNodes> 0 -1 120 -137080576 -679742128 -540480048 -336070672 -102828728 131593200 133169151 91187187</internalNodes>
          <leafValues>
            -0.4449204802513123 0.4490709304809570</leafValues></_>
        
        <_>
          <internalNodes> 0 -1 89 4413678672 30726906224 -201608976 -2147549200 -38273812 -31612932 -22626719 -28311569</internalNodes>
          <leafValues>
            -0.4693818688392639 0.4061094820499420</leafValues></_>
        
        <_>
          <internalNodes> 0 -1 14 -268471056 32010925936 -537668400 -2415954064 -50348320 -8 -34635792 -33157468</internalNodes>
          <leafValues>
            -0.3600351214408875 0.5056326985359192</leafValues></_>
        
        <_>
          <internalNodes> 0 -1 67 -25735900400 -76091664 -17330602000 -1141850192 384 27197884 91715583 127918219</internalNodes>
          <leafValues>
            -0.4459891915321350 0.4132415652275085</leafValues></_>
        
        <_>
          <internalNodes> 0 -1 86 -6654788624 -4323347328 -17412689808 -13204979712 -2605572 -205064 115834872 -26294539</internalNodes>
          <leafValues>
            -0.4466069042682648 0.4135067760944367</leafValues></_>
        
        <_>
          <internalNodes> 0 -1 80 -8672130640 -5709311040 -17458005520 -17180750352 -7336944 -2637712 130023403 -11794</internalNodes>
          <leafValues>
            -0.3394956290721893 0.5658645033836365</leafValues></_>
        
        <_>
          <internalNodes> 0 -1 75 17179849712 -4515187856 -6652184784 2734350896 -17301876 86169652 -83886371 47329506</internalNodes>
          <leafValues>
            -0.5346512198448181 0.3584479391574860</leafValues></_>
        
        <_>
          <internalNodes> 0 -1 55 -17718915104 -262160 -12901756944 -6259020336 -49754736 -7697928 132104190 -13595651</internalNodes>
          <leafValues>
            -0.4379335641860962 0.4123645126819611</leafValues></_></weakClassifiers></_>
    
    <_>
      <maxWeakCount>10</maxWeakCount>
      <stageThreshold>-0.8402050137519836</stageThreshold>
      <weakClassifiers>
        
        <_>
          <internalNodes> 0 -1 71 -19397118384 -20669562896 -1090558240 -7517278736 -55640412 970364 -30480655 2944764</internalNodes>
          <leafValues>
            -0.2670986354351044 0.6014143228530884</leafValues></_>
        
        <_>
          <internalNodes> 0 -1 31 -17184260240 -13447102480 34355543792 -4194320 -85073792 -118625552 -68161800 -17838129</internalNodes>
          <leafValues>
            -0.4149844348430634 0.4670888185501099</leafValues></_>
        
        <_>
          <internalNodes> 0 -1 40 -8131719232 -345014288 -671360016 -1040 89136912 118710264 133920737 -8912969</internalNodes>
          <leafValues>
            -0.4985891580581665 0.3719584941864014</leafValues></_>
        
        <_>
          <internalNodes> 0 -1 109 31593053200 -243270640 14750522128 -3040932944 -12583620 658992 -14781131 -46637224</internalNodes>
          <leafValues>
            -0.4568729996681213 0.3965812027454376</leafValues></_>
        
        <_>
          <internalNodes> 0 -1 130 -7049606272 -2130096 -5740975232 -32065418336 -37189168 -41025120 -16790577 -35718168</internalNodes>
          <leafValues>
            -0.4770836830139160 0.3862601518630981</leafValues></_>
        
        <_>
          <internalNodes> 0 -1 66 -21767419088 -24905798880 -9745736736 11736750928 58854668 -69242632 83299319 -4230688</internalNodes>
          <leafValues>
            -0.4877715110778809 0.3778986334800720</leafValues></_>
        
        <_>
          <internalNodes> 0 -1 49 -14918301504 -20936718224 -8522167648 -1584677712 -1069684 -15003840 97054472 -5173475</internalNodes>
          <leafValues>
            -0.3721654713153839 0.4994400143623352</leafValues></_>
        
        <_>
          <internalNodes> 0 -1 133 -7981747552 8950677712 -30856951120 -4580230160 -40994124 87843912 -58700322 117808076</internalNodes>
          <leafValues>
            -0.3934195041656494 0.4769641458988190</leafValues></_>
        
        <_>
          <internalNodes> 0 -1 0 14897538928 4025807792 32212254672 -10739715152 -20989860 116292328 -5 -121636639</internalNodes>
          <leafValues>
            -0.4323300719261169 0.4342164099216461</leafValues></_>
        
        <_>
          <internalNodes> 0 -1 103 -8578819104 -26311755648 12912144304 17105438880 2360588 -8610792 23418268 125166646</internalNodes>
          <leafValues>
            -0.4993278682231903 0.3665378093719482</leafValues></_></weakClassifiers></_>
    
    <_>
      <maxWeakCount>9</maxWeakCount>
      <stageThreshold>-1.1974394321441650</stageThreshold>
      <weakClassifiers>
        
        <_>
          <internalNodes> 0 -1 43 -263200 -4112 -3221575040 -1141331296 -344 134216428 133954091 -281941</internalNodes>
          <leafValues>
            -0.3310225307941437 0.5624626278877258</leafValues></_>
        
        <_>
          <internalNodes> 0 -1 90 -10266651904 -12616394224 -18365836672 -2158281008 -8552640 -31208168 125953186 -5444195</internalNodes>
          <leafValues>
            -0.5266560912132263 0.3704403042793274</leafValues></_>
        
        <_>
          <internalNodes> 0 -1 104 -268440816 -31146910160 -26343417520 -13426111152 -9175052 -111273032 131948127 -8806542</internalNodes>
          <leafValues>
            -0.4171888828277588 0.4540435671806335</leafValues></_>
        
        <_>
          <internalNodes> 0 -1 85 -14917104000 -31958507568 -536883216 -1107296272 -52003376 -61353984 -18874392 -36175880</internalNodes>
          <leafValues>
            -0.4556705355644226 0.3704262077808380</leafValues></_>
        
        <_>
          <internalNodes> 0 -1 24 17807179808 -4757109008 22062196656 -2231507088 -7405776 -75564176 69938989 -83394584</internalNodes>
          <leafValues>
            -0.4182529747486115 0.4267231225967407</leafValues></_>
        
        <_>
          <internalNodes> 0 -1 78 -25072940160 -27496807424 -5477040192 -17199555632 -107148912 -147104 -7005934 -34350818</internalNodes>
          <leafValues>
            -0.3625369668006897 0.4684656262397766</leafValues></_>
        
        <_>
          <internalNodes> 0 -1 5 33876277040 -4174428304 -9943388144 -1417724320 -5326228 19802272 -2079 119060643</internalNodes>
          <leafValues>
            -0.4742925167083740 0.3689507246017456</leafValues></_>
        
        <_>
          <internalNodes> 0 -1 11 -33294398032 18329108464 -2290123408 -2432704592 -18415876 -22100224 -102572480 -3145745</internalNodes>
          <leafValues>
            -0.3666271567344666 0.4580127298831940</leafValues></_>
        
        <_>
          <internalNodes> 0 -1 32 -17137087728 -10581526656 -9333412432 16963048976 117965852 -39909104 -117373551 -2145060</internalNodes>
          <leafValues>
            -0.4567637443542481 0.3894708156585693</leafValues></_></weakClassifiers></_>
    
    <_>
      <maxWeakCount>9</maxWeakCount>
      <stageThreshold>-0.5733128190040588</stageThreshold>
      <weakClassifiers>
        
        <_>
          <internalNodes> 0 -1 122 17641065808 18647841648 -1946875104 -2155906064 -62128956 68046588 -19927319 -19992586</internalNodes>
          <leafValues>
            -0.4055117964744568 0.5487945079803467</leafValues></_>
        
        <_>
          <internalNodes> 0 -1 68 -8464 -329488 -328080 -24982429664 -17827076 -33687056 113245949 -23077125</internalNodes>
          <leafValues>
            -0.3787897229194641 0.4532003402709961</leafValues></_>
        
        <_>
          <internalNodes> 0 -1 58 -19617141872 -9134530816 7312425904 16000330672 -83452852 123057320 121303855 33551023</internalNodes>
          <leafValues>
            -0.4258328974246979 0.4202791750431061</leafValues></_>
        
        <_>
          <internalNodes> 0 -1 94 -9742068672 -12884907056 -4308867904 -285442672 -85019916 -123737368 -3152203 -1165404</internalNodes>
          <leafValues>
            -0.4561023116111755 0.4002747833728790</leafValues></_>
        
        <_>
          <internalNodes> 0 -1 87 732229360 -17448833040 -12365541392 -9127429152 128922868 -1028 -79692545 -1025</internalNodes>
          <leafValues>
            -0.4314672648906708 0.4086346626281738</leafValues></_>
        
        <_>
          <internalNodes> 0 -1 127 -33324287504 20653694192 31901166944 -15846105744 -33556000 67551100 -46139643 -60342419</internalNodes>
          <leafValues>
            -0.4174543321132660 0.4249868988990784</leafValues></_>
        
        <_>
          <internalNodes> 0 -1 3 10707594736 9938667744 17384108912 23580302512 -51183936 10545680 -18350651 -4953084</internalNodes>
          <leafValues>
            -0.4321364760398865 0.4090838730335236</leafValues></_>
        
        <_>
          <internalNodes> 0 -1 79 -9917493504 -18889768496 -17311847504 16691254224 -4305980 -4194232 -88394742 -52604760</internalNodes>
          <leafValues>
            -0.5018386244773865 0.3702533841133118</leafValues></_>
        
        <_>
          <internalNodes> 0 -1 116 -1849873184 -19132598256 -17536389856 -34247559120 -3375132 -33967856 -132805151 -89840366</internalNodes>
          <leafValues>
            -0.5037505626678467 0.3564981222152710</leafValues></_></weakClassifiers></_>
    
    <_>
      <maxWeakCount>9</maxWeakCount>
      <stageThreshold>-0.4892596900463104</stageThreshold>
      <weakClassifiers>
        
        <_>
          <internalNodes> 0 -1 132 -44032 32035796368 -4370476032 30995576624 -4194572 125238004 116383444 52903870</internalNodes>
          <leafValues>
            -0.2448196411132813 0.5689709186553955</leafValues></_>
        
        <_>
          <internalNodes> 0 -1 62 -20629733760 -26412961728 -14280647984 -22925242944 73713992 -4879056 -38239972 -33697993</internalNodes>
          <leafValues>
            -0.4633283913135529 0.3587929606437683</leafValues></_>
        
        <_>
          <internalNodes> 0 -1 23 -444598800 -21349599376 -8762607696 -2172750784 -17825792 -4903172 -41013251 -16503131</internalNodes>
          <leafValues>
            -0.3731099069118500 0.4290455579757690</leafValues></_>
        
        <_>
          <internalNodes> 0 -1 77 -17291051760 15218047888 -22217295184 -18459479568 21366464 25231376 -34411776 100012158</internalNodes>
          <leafValues>
            -0.3658909499645233 0.4556473195552826</leafValues></_>
        
        <_>
          <internalNodes> 0 -1 22 -19058412704 11291080208 7315253040 -1212911312 -36680040 -12801968 -6290287 -2457471</internalNodes>
          <leafValues>
            -0.5214384198188782 0.3221037387847900</leafValues></_>
        
        <_>
          <internalNodes> 0 -1 72 -4225817568 2230784 -2933919712 -3271594256 -26034176 34119460 -42107262 -48472465</internalNodes>
          <leafValues>
            -0.4289036989212036 0.4004956185817719</leafValues></_>
        
        <_>
          <internalNodes> 0 -1 50 21575856096 -971371408 -17757655824 -10142550608 -64156560 -36855756 -108781246 -97735656</internalNodes>
          <leafValues>
            -0.4621542394161224 0.3832748532295227</leafValues></_>
        
        <_>
          <internalNodes> 0 -1 108 -28638774656 -25792914896 -12884907088 -22653473808 -90554516 -29868440 -111149413 -48276132</internalNodes>
          <leafValues>
            -0.3711548447608948 0.4612701535224915</leafValues></_>
        
        <_>
          <internalNodes> 0 -1 92 -4561659600 -1194128096 29944945328 16927293600 25494088 -36403124 3290921 -80904</internalNodes>
          <leafValues>
            -0.5180652141571045 0.3205870389938355</leafValues></_></weakClassifiers></_>
    
    <_>
      <maxWeakCount>10</maxWeakCount>
      <stageThreshold>-0.5911940932273865</stageThreshold>
      <weakClassifiers>
        
        <_>
          <internalNodes> 0 -1 81 29410626368 -1186460032 -1450463808 -17188222336 256 -78722736 -52916964 -6306403</internalNodes>
          <leafValues>
            -0.2592592537403107 0.5873016119003296</leafValues></_>
        
        <_>
          <internalNodes> 0 -1 1 19327348688 18513655536 33554137040 -33554704 -17826048 -51450436 -67849 -67584</internalNodes>
          <leafValues>
            -0.3801195919513702 0.4718827307224274</leafValues></_>
        
        <_>
          <internalNodes> 0 -1 121 -604247872 -13857991472 -5100517248 -22280146960 -776 -33554696 134217397 133169143</internalNodes>
          <leafValues>
            -0.3509117066860199 0.5094807147979736</leafValues></_>
        
        <_>
          <internalNodes> 0 -1 38 -267360 -16 -134501456 -1082608656 134215600 -1296 -1049672 121617071</internalNodes>
          <leafValues>
            -0.4068757295608521 0.4130136370658875</leafValues></_>
        
        <_>
          <internalNodes> 0 -1 17 -7667223488 -7163879184 21667672064 -4190150864 -9699480 54132324 103212967 34267050</internalNodes>
          <leafValues>
            -0.4557141065597534 0.3539792001247406</leafValues></_>
        
        <_>
          <internalNodes> 0 -1 100 -20596187120 22298301456 -180386912 -3422552336 -14082460 -15730128 -30798999 -49521361</internalNodes>
          <leafValues>
            -0.4117803275585175 0.4118592441082001</leafValues></_>
        
        <_>
          <internalNodes> 0 -1 63 -14768177104 -34164823312 -33057675888 -16680919056 -23888756 -125129544 -3212800 -23200097</internalNodes>
          <leafValues>
            -0.4008397758007050 0.4034757018089294</leafValues></_>
        
        <_>
          <internalNodes> 0 -1 101 -1684292288 -22974295120 -10210030208 -16977714016 -39209608 -3018444 98825247 -27266163</internalNodes>
          <leafValues>
            -0.5694189667701721 0.2964762747287750</leafValues></_>
        
        <_>
          <internalNodes> 0 -1 118 -201326640 -9193915824 -15910364624 -26373792336 -524948 66131728 -38813922 -15687716</internalNodes>
          <leafValues>
            -0.3195341229438782 0.5294018983840942</leafValues></_>
        
        <_>
          <internalNodes> 0 -1 92 -28541465632 -78130192 -7321157664 -17231206144 -21771488 -67399344 107372527 22795998</internalNodes>
          <leafValues>
            -0.3365339040756226 0.5067458748817444</leafValues></_></weakClassifiers></_>
    
    <_>
      <maxWeakCount>10</maxWeakCount>
      <stageThreshold>-0.7612916231155396</stageThreshold>
      <weakClassifiers>
        
        <_>
          <internalNodes> 0 -1 10 697457424 -7258206080 22967520000 -17239016976 -123541332 -17997348 -103718570 -48879</internalNodes>
          <leafValues>
            -0.4204545319080353 0.5165745615959168</leafValues></_>
        
        <_>
          <internalNodes> 0 -1 131 32747412656 -33086931120 23576059392 -12633277392 -4194432 929684 -8914573 -83682690</internalNodes>
          <leafValues>
            -0.3762553930282593 0.4075302779674530</leafValues></_>
        
        <_>
          <internalNodes> 0 -1 83 -16836624 -17181020096 -8623538464 -5688368608 -17050892 -98564 -69917 -19072257</internalNodes>
          <leafValues>
            -0.4253497421741486 0.3728055357933044</leafValues></_>
        
        <_>
          <internalNodes> 0 -1 135 -2550255536 31907607824 -15579809568 -3254784080 -136 -13405388 -33657172 35859187</internalNodes>
          <leafValues>
            -0.3601998090744019 0.4563256204128265</leafValues></_>
        
        <_>
          <internalNodes> 0 -1 115 -20903379072 -19138392288 -24476284448 10930237168 -16314480 -83148080 -40116288 64348143</internalNodes>
          <leafValues>
            -0.4034293889999390 0.4160816967487335</leafValues></_>
        
        <_>
          <internalNodes> 0 -1 64 -22933844288 -317915440 -30735037824 -20471313008 -35812100 -2127664 -26116 -6944</internalNodes>
          <leafValues>
            -0.3620899617671967 0.4594142735004425</leafValues></_>
        
        <_>
          <internalNodes> 0 -1 36 32264955680 -6892493584 -12797890640 -265290320 -39142192 -38453560 103246626 50335399</internalNodes>
          <leafValues>
            -0.3903816640377045 0.4381459355354309</leafValues></_>
        
        <_>
          <internalNodes> 0 -1 93 -29629982272 -19114193232 -18456346688 -17734391584 84674828 -68184848 123526141 -83906386</internalNodes>
          <leafValues>
            -0.3591445386409760 0.4624078869819641</leafValues></_>
        
        <_>
          <internalNodes> 0 -1 91 12780764000 -4408216736 10370677680 -18325717600 4259856 75710516 -19047470 66438571</internalNodes>
          <leafValues>
            -0.4297670423984528 0.4023293554782867</leafValues></_>
        
        <_>
          <internalNodes> 0 -1 107 -8727302224 -21207450320 -6087147776 -16935574176 -34144888 -101785600 -10223621 -33562644</internalNodes>
          <leafValues>
            -0.5727006793022156 0.2995934784412384</leafValues></_></weakClassifiers></_></stages>
  <features>
    <_>
      <rect> 15 9 3 5 </rect></_>
    <_>
      <rect> 12 18 4 2 </rect></_>
    <_>
      <rect> 6 15 6 3 </rect></_>
    <_>
      <rect> 18 14 2 3 </rect></_>
    <_>
      <rect> 15 14 3 3 </rect></_>
    <_>
      <rect> 15 2 3 7 </rect></_>
    <_>
      <rect> 15 11 3 3 </rect></_>
    <_>
      <rect> 15 1 3 4 </rect></_>
    <_>
      <rect> 0 0 8 4 </rect></_>
    <_>
      <rect> 12 1 4 3 </rect></_>
    <_>
      <rect> 8 15 5 3 </rect></_>
    <_>
      <rect> 17 17 2 2 </rect></_>
    <_>
      <rect> 14 18 3 1 </rect></_>
    <_>
      <rect> 11 5 4 4 </rect></_>
    <_>
      <rect> 17 6 2 2 </rect></_>
    <_>
      <rect> 11 8 4 1 </rect></_>
    <_>
      <rect> 11 1 4 3 </rect></_>
    <_>
      <rect> 14 1 3 2 </rect></_>
    <_>
      <rect> 16 15 2 3 </rect></_>
    <_>
      <rect> 16 17 2 2 </rect></_>
    <_>
      <rect> 10 4 4 6 </rect></_>
    <_>
      <rect> 10 9 4 4 </rect></_>
    <_>
      <rect> 16 14 2 1 </rect></_>
    <_>
      <rect> 16 4 2 3 </rect></_>
    <_>
      <rect> 13 1 3 2 </rect></_>
    <_>
      <rect> 15 18 2 2 </rect></_>
    <_>
      <rect> 0 14 7 3 </rect></_>
    <_>
      <rect> 15 14 2 1 </rect></_>
    <_>
      <rect> 15 5 2 4 </rect></_>
    <_>
      <rect> 15 0 2 2 </rect></_>
    <_>
      <rect> 14 15 2 3 </rect></_>
    <_>
      <rect> 14 18 2 1 </rect></_>
    <_>
      <rect> 14 15 2 1 </rect></_>
    <_>
      <rect> 14 3 2 5 </rect></_>
    <_>
      <rect> 5 11 5 2 </rect></_>
    <_>
      <rect> 8 7 4 3 </rect></_>
    <_>
      <rect> 14 0 2 2 </rect></_>
    <_>
      <rect> 13 18 2 2 </rect></_>
    <_>
      <rect> 7 9 4 4 </rect></_>
    <_>
      <rect> 13 3 2 5 </rect></_>
    <_>
      <rect> 13 9 2 2 </rect></_>
    <_>
      <rect> 13 8 2 2 </rect></_>
    <_>
      <rect> 6 9 4 4 </rect></_>
    <_>
      <rect> 6 11 4 3 </rect></_>
    <_>
      <rect> 12 10 2 3 </rect></_>
    <_>
      <rect> 12 4 2 5 </rect></_>
    <_>
      <rect> 6 10 4 3 </rect></_>
    <_>
      <rect> 6 12 4 2 </rect></_>
    <_>
      <rect> 6 6 4 4 </rect></_>
    <_>
      <rect> 15 0 1 2 </rect></_>
    <_>
      <rect> 12 0 2 1 </rect></_>
    <_>
      <rect> 8 3 3 7 </rect></_>
    <_>
      <rect> 11 11 2 3 </rect></_>
    <_>
      <rect> 2 12 5 1 </rect></_>
    <_>
      <rect> 11 0 2 1 </rect></_>
    <_>
      <rect> 13 12 1 4 </rect></_>
    <_>
      <rect> 10 13 2 2 </rect></_>
    <_>
      <rect> 7 13 3 2 </rect></_>
    <_>
      <rect> 7 4 3 1 </rect></_>
    <_>
      <rect> 13 0 1 2 </rect></_>
    <_>
      <rect> 0 15 5 3 </rect></_>
    <_>
      <rect> 9 4 2 6 </rect></_>
    <_>
      <rect> 12 16 1 1 </rect></_>
    <_>
      <rect> 12 10 1 1 </rect></_>
    <_>
      <rect> 12 5 1 1 </rect></_>
    <_>
      <rect> 9 5 2 1 </rect></_>
    <_>
      <rect> 12 4 1 1 </rect></_>
    <_>
      <rect> 12 3 1 1 </rect></_>
    <_>
      <rect> 11 13 1 2 </rect></_>
    <_>
      <rect> 5 10 3 3 </rect></_>
    <_>
      <rect> 11 2 1 5 </rect></_>
    <_>
      <rect> 11 13 1 1 </rect></_>
    <_>
      <rect> 11 12 1 1 </rect></_>
    <_>
      <rect> 11 11 1 1 </rect></_>
    <_>
      <rect> 11 8 1 2 </rect></_>
    <_>
      <rect> 5 1 3 3 </rect></_>
    <_>
      <rect> 11 6 1 1 </rect></_>
    <_>
      <rect> 8 6 2 1 </rect></_>
    <_>
      <rect> 11 5 1 1 </rect></_>
    <_>
      <rect> 8 5 2 1 </rect></_>
    <_>
      <rect> 11 4 1 1 </rect></_>
    <_>
      <rect> 11 0 1 1 </rect></_>
    <_>
      <rect> 7 15 2 2 </rect></_>
    <_>
      <rect> 10 13 1 2 </rect></_>
    <_>
      <rect> 4 10 3 3 </rect></_>
    <_>
      <rect> 1 1 4 6 </rect></_>
    <_>
      <rect> 10 15 1 1 </rect></_>
    <_>
      <rect> 7 11 2 2 </rect></_>
    <_>
      <rect> 10 10 1 2 </rect></_>
    <_>
      <rect> 10 11 1 1 </rect></_>
    <_>
      <rect> 10 8 1 2 </rect></_>
    <_>
      <rect> 10 6 1 1 </rect></_>
    <_>
      <rect> 10 4 1 1 </rect></_>
    <_>
      <rect> 10 3 1 1 </rect></_>
    <_>
      <rect> 6 18 2 2 </rect></_>
    <_>
      <rect> 6 8 2 5 </rect></_>
    <_>
      <rect> 0 19 4 1 </rect></_>
    <_>
      <rect> 9 12 1 3 </rect></_>
    <_>
      <rect> 3 5 3 4 </rect></_>
    <_>
      <rect> 3 8 3 2 </rect></_>
    <_>
      <rect> 9 10 1 1 </rect></_>
    <_>
      <rect> 3 6 3 2 </rect></_>
    <_>
      <rect> 0 1 4 3 </rect></_>
    <_>
      <rect> 9 4 1 1 </rect></_>
    <_>
      <rect> 6 0 2 1 </rect></_>
    <_>
      <rect> 5 3 2 5 </rect></_>
    <_>
      <rect> 2 2 3 5 </rect></_>
    <_>
      <rect> 2 7 3 2 </rect></_>
    <_>
      <rect> 5 1 2 2 </rect></_>
    <_>
      <rect> 2 1 3 2 </rect></_>
    <_>
      <rect> 8 0 1 2 </rect></_>
    <_>
      <rect> 5 0 2 2 </rect></_>
    <_>
      <rect> 4 18 2 2 </rect></_>
    <_>
      <rect> 7 14 1 3 </rect></_>
    <_>
      <rect> 1 16 3 2 </rect></_>
    <_>
      <rect> 4 14 2 1 </rect></_>
    <_>
      <rect> 4 8 2 1 </rect></_>
    <_>
      <rect> 1 2 3 3 </rect></_>
    <_>
      <rect> 4 1 2 2 </rect></_>
    <_>
      <rect> 3 18 2 2 </rect></_>
    <_>
      <rect> 3 15 2 3 </rect></_>
    <_>
      <rect> 0 14 3 2 </rect></_>
    <_>
      <rect> 0 2 3 6 </rect></_>
    <_>
      <rect> 0 12 3 2 </rect></_>
    <_>
      <rect> 0 1 3 4 </rect></_>
    <_>
      <rect> 0 5 3 2 </rect></_>
    <_>
      <rect> 3 1 2 2 </rect></_>
    <_>
      <rect> 0 1 3 2 </rect></_>
    <_>
      <rect> 2 14 2 3 </rect></_>
    <_>
      <rect> 2 9 2 4 </rect></_>
    <_>
      <rect> 5 15 1 1 </rect></_>
    <_>
      <rect> 2 2 2 2 </rect></_>
    <_>
      <rect> 1 17 2 2 </rect></_>
    <_>
      <rect> 1 8 2 5 </rect></_>
    <_>
      <rect> 1 6 2 2 </rect></_>
    <_>
      <rect> 0 18 2 2 </rect></_></features></cascade>
</opencv_storage>